{
  "quarter": "2025-Q3",
  "category": "guru",
  "fundTopHoldings": [
    {
      "fundName": "Berkshire Hathaway Inc.",
      "fundCik": "0001067983",
      "mostPurchased": {
        "ticker": "AXP",
        "companyName": "AMERICAN EXPRESS CO",
        "cusip": "025816109",
        "value": 49512116707,
        "shares": 149061045,
        "percentOfPortfolio": 18.52066094908105,
        "positionChange": {
          "previousQuarter": {
            "value": 0,
            "shares": 0,
            "percentOfPortfolio": 0
          },
          "currentQuarter": {
            "value": 49512116707,
            "shares": 149061045,
            "percentOfPortfolio": 18.52066094908105
          },
          "change": {
            "valueChange": 49512116707,
            "sharesChange": 149061045,
            "percentChange": null
          }
        },
        "priceHistory": [
          {
            "date": "2025-10-08",
            "close": 322.29
          },
          {
            "date": "2025-10-09",
            "close": 322.9
          },
          {
            "date": "2025-10-10",
            "close": 315.56
          },
          {
            "date": "2025-10-13",
            "close": 322.4
          },
          {
            "date": "2025-10-14",
            "close": 332.11
          },
          {
            "date": "2025-10-15",
            "close": 329.93
          },
          {
            "date": "2025-10-16",
            "close": 322.4
          },
          {
            "date": "2025-10-17",
            "close": 345.85
          },
          {
            "date": "2025-10-20",
            "close": 348.71
          },
          {
            "date": "2025-10-21",
            "close": 354.43
          },
          {
            "date": "2025-10-22",
            "close": 351.22
          },
          {
            "date": "2025-10-23",
            "close": 354.14
          },
          {
            "date": "2025-10-24",
            "close": 356.77
          },
          {
            "date": "2025-10-27",
            "close": 360.87
          },
          {
            "date": "2025-10-28",
            "close": 360.23
          },
          {
            "date": "2025-10-29",
            "close": 357.43
          },
          {
            "date": "2025-10-30",
            "close": 358.08
          },
          {
            "date": "2025-10-31",
            "close": 359.93
          },
          {
            "date": "2025-11-03",
            "close": 360.82
          },
          {
            "date": "2025-11-04",
            "close": 359.69
          },
          {
            "date": "2025-11-05",
            "close": 364.99
          },
          {
            "date": "2025-11-06",
            "close": 364.92
          },
          {
            "date": "2025-11-07",
            "close": 367.72
          },
          {
            "date": "2025-11-10",
            "close": 367.06
          },
          {
            "date": "2025-11-11",
            "close": 369.34
          },
          {
            "date": "2025-11-12",
            "close": 371.94
          },
          {
            "date": "2025-11-13",
            "close": 363.92
          },
          {
            "date": "2025-11-14",
            "close": 356.39
          },
          {
            "date": "2025-11-17",
            "close": 340.49
          },
          {
            "date": "2025-11-18",
            "close": 339.9
          },
          {
            "date": "2025-11-19",
            "close": 343.88
          },
          {
            "date": "2025-11-20",
            "close": 343.04
          },
          {
            "date": "2025-11-21",
            "close": 352.11
          },
          {
            "date": "2025-11-24",
            "close": 355.14
          },
          {
            "date": "2025-11-25",
            "close": 361.84
          },
          {
            "date": "2025-11-26",
            "close": 363.16
          },
          {
            "date": "2025-11-28",
            "close": 364.46
          },
          {
            "date": "2025-12-01",
            "close": 359.51
          },
          {
            "date": "2025-12-02",
            "close": 359.9
          },
          {
            "date": "2025-12-03",
            "close": 367.31
          },
          {
            "date": "2025-12-04",
            "close": 370.33
          },
          {
            "date": "2025-12-05",
            "close": 369.53
          },
          {
            "date": "2025-12-08",
            "close": 361.48
          },
          {
            "date": "2025-12-09",
            "close": 363.1
          },
          {
            "date": "2025-12-10",
            "close": 374.74
          },
          {
            "date": "2025-12-11",
            "close": 384.04
          },
          {
            "date": "2025-12-12",
            "close": 381.71
          },
          {
            "date": "2025-12-15",
            "close": 381.72
          },
          {
            "date": "2025-12-16",
            "close": 379.91
          },
          {
            "date": "2025-12-17",
            "close": 374.78
          },
          {
            "date": "2025-12-18",
            "close": 374.69
          },
          {
            "date": "2025-12-19",
            "close": 375.68
          },
          {
            "date": "2025-12-22",
            "close": 380.01
          },
          {
            "date": "2025-12-23",
            "close": 381.34
          },
          {
            "date": "2025-12-24",
            "close": 382.26
          },
          {
            "date": "2025-12-26",
            "close": 380.21
          },
          {
            "date": "2025-12-29",
            "close": 374.49
          },
          {
            "date": "2025-12-30",
            "close": 372.56
          },
          {
            "date": "2025-12-31",
            "close": 369.13
          },
          {
            "date": "2026-01-02",
            "close": 372.73
          },
          {
            "date": "2026-01-05",
            "close": 379.8
          }
        ],
        "valuationMetrics": {
          "peRatio": 25.50705,
          "pbRatio": 8.072434,
          "psRatio": 4.047785,
          "evToEbitda": null,
          "marketCap": 264296071168,
          "lastUpdated": "2026-01-06T17:19:47.150828"
        }
      },
      "category": "guru",
      "metadata": {
        "knownFor": "Value investing",
        "since": 1965,
        "type": "conglomerate"
      }
    },
    {
      "fundName": "Pershing Square Capital Management",
      "fundCik": "0001336528",
      "mostPurchased": {
        "ticker": "GOOGL",
        "companyName": "ALPHABET INC",
        "cusip": "02079K107",
        "value": 1540217750,
        "shares": 6324031,
        "percentOfPortfolio": 10.518246608362263,
        "positionChange": {
          "previousQuarter": {
            "value": 1121819859,
            "shares": 6324031,
            "percentOfPortfolio": 8.171097750242179
          },
          "currentQuarter": {
            "value": 1540217750,
            "shares": 6324031,
            "percentOfPortfolio": 10.518246608362263
          },
          "change": {
            "valueChange": 418397891,
            "sharesChange": 0,
            "percentChange": 37.29635267581762
          }
        },
        "priceHistory": [
          {
            "date": "2025-10-08",
            "close": 244.46
          },
          {
            "date": "2025-10-09",
            "close": 241.37
          },
          {
            "date": "2025-10-10",
            "close": 236.42
          },
          {
            "date": "2025-10-13",
            "close": 243.99
          },
          {
            "date": "2025-10-14",
            "close": 245.29
          },
          {
            "date": "2025-10-15",
            "close": 250.87
          },
          {
            "date": "2025-10-16",
            "close": 251.3
          },
          {
            "date": "2025-10-17",
            "close": 253.13
          },
          {
            "date": "2025-10-20",
            "close": 256.38
          },
          {
            "date": "2025-10-21",
            "close": 250.3
          },
          {
            "date": "2025-10-22",
            "close": 251.53
          },
          {
            "date": "2025-10-23",
            "close": 252.91
          },
          {
            "date": "2025-10-24",
            "close": 259.75
          },
          {
            "date": "2025-10-27",
            "close": 269.09
          },
          {
            "date": "2025-10-28",
            "close": 267.3
          },
          {
            "date": "2025-10-29",
            "close": 274.39
          },
          {
            "date": "2025-10-30",
            "close": 281.3
          },
          {
            "date": "2025-10-31",
            "close": 281.01
          },
          {
            "date": "2025-11-03",
            "close": 283.53
          },
          {
            "date": "2025-11-04",
            "close": 277.36
          },
          {
            "date": "2025-11-05",
            "close": 284.12
          },
          {
            "date": "2025-11-06",
            "close": 284.56
          },
          {
            "date": "2025-11-07",
            "close": 278.65
          },
          {
            "date": "2025-11-10",
            "close": 289.91
          },
          {
            "date": "2025-11-11",
            "close": 291.12
          },
          {
            "date": "2025-11-12",
            "close": 286.52
          },
          {
            "date": "2025-11-13",
            "close": 278.39
          },
          {
            "date": "2025-11-14",
            "close": 276.23
          },
          {
            "date": "2025-11-17",
            "close": 284.83
          },
          {
            "date": "2025-11-18",
            "close": 284.09
          },
          {
            "date": "2025-11-19",
            "close": 292.62
          },
          {
            "date": "2025-11-20",
            "close": 289.26
          },
          {
            "date": "2025-11-21",
            "close": 299.46
          },
          {
            "date": "2025-11-24",
            "close": 318.37
          },
          {
            "date": "2025-11-25",
            "close": 323.23
          },
          {
            "date": "2025-11-26",
            "close": 319.74
          },
          {
            "date": "2025-11-28",
            "close": 319.97
          },
          {
            "date": "2025-12-01",
            "close": 314.68
          },
          {
            "date": "2025-12-02",
            "close": 315.6
          },
          {
            "date": "2025-12-03",
            "close": 319.42
          },
          {
            "date": "2025-12-04",
            "close": 317.41
          },
          {
            "date": "2025-12-05",
            "close": 321.06
          },
          {
            "date": "2025-12-08",
            "close": 313.72
          },
          {
            "date": "2025-12-09",
            "close": 317.08
          },
          {
            "date": "2025-12-10",
            "close": 320.21
          },
          {
            "date": "2025-12-11",
            "close": 312.43
          },
          {
            "date": "2025-12-12",
            "close": 309.29
          },
          {
            "date": "2025-12-15",
            "close": 308.22
          },
          {
            "date": "2025-12-16",
            "close": 306.57
          },
          {
            "date": "2025-12-17",
            "close": 296.72
          },
          {
            "date": "2025-12-18",
            "close": 302.46
          },
          {
            "date": "2025-12-19",
            "close": 307.16
          },
          {
            "date": "2025-12-22",
            "close": 309.78
          },
          {
            "date": "2025-12-23",
            "close": 314.35
          },
          {
            "date": "2025-12-24",
            "close": 314.09
          },
          {
            "date": "2025-12-26",
            "close": 313.51
          },
          {
            "date": "2025-12-29",
            "close": 313.56
          },
          {
            "date": "2025-12-30",
            "close": 313.85
          },
          {
            "date": "2025-12-31",
            "close": 313
          },
          {
            "date": "2026-01-02",
            "close": 315.15
          },
          {
            "date": "2026-01-05",
            "close": 316.54
          }
        ],
        "valuationMetrics": {
          "peRatio": 31.24778,
          "pbRatio": 9.881684,
          "psRatio": 9.94607,
          "evToEbitda": 25.937,
          "marketCap": 3833971081216,
          "lastUpdated": "2026-01-06T17:19:47.663190"
        }
      },
      "category": "guru",
      "metadata": {
        "knownFor": "Activist investing",
        "since": 2003,
        "type": "hedge fund"
      }
    },
    {
      "fundName": "Icahn Enterprises L.P.",
      "fundCik": "0000914208",
      "mostPurchased": {
        "ticker": "NVDA",
        "companyName": "NVIDIA CORPORATION",
        "cusip": "67066G104",
        "value": 13417232370,
        "shares": 71911418,
        "percentOfPortfolio": 2.1138709475929436,
        "positionChange": {
          "previousQuarter": {
            "value": 92792267,
            "shares": 587330,
            "percentOfPortfolio": 0.015781260163569805
          },
          "currentQuarter": {
            "value": 13417232370,
            "shares": 71911418,
            "percentOfPortfolio": 2.1138709475929436
          },
          "change": {
            "valueChange": 13324440103,
            "sharesChange": 71324088,
            "percentChange": 14359.42943715342
          }
        },
        "priceHistory": [
          {
            "date": "2025-10-08",
            "close": 189.1
          },
          {
            "date": "2025-10-09",
            "close": 192.56
          },
          {
            "date": "2025-10-10",
            "close": 183.15
          },
          {
            "date": "2025-10-13",
            "close": 188.31
          },
          {
            "date": "2025-10-14",
            "close": 180.02
          },
          {
            "date": "2025-10-15",
            "close": 179.82
          },
          {
            "date": "2025-10-16",
            "close": 181.8
          },
          {
            "date": "2025-10-17",
            "close": 183.21
          },
          {
            "date": "2025-10-20",
            "close": 182.63
          },
          {
            "date": "2025-10-21",
            "close": 181.15
          },
          {
            "date": "2025-10-22",
            "close": 180.27
          },
          {
            "date": "2025-10-23",
            "close": 182.15
          },
          {
            "date": "2025-10-24",
            "close": 186.25
          },
          {
            "date": "2025-10-27",
            "close": 191.48
          },
          {
            "date": "2025-10-28",
            "close": 201.02
          },
          {
            "date": "2025-10-29",
            "close": 207.03
          },
          {
            "date": "2025-10-30",
            "close": 202.88
          },
          {
            "date": "2025-10-31",
            "close": 202.48
          },
          {
            "date": "2025-11-03",
            "close": 206.87
          },
          {
            "date": "2025-11-04",
            "close": 198.68
          },
          {
            "date": "2025-11-05",
            "close": 195.2
          },
          {
            "date": "2025-11-06",
            "close": 188.07
          },
          {
            "date": "2025-11-07",
            "close": 188.14
          },
          {
            "date": "2025-11-10",
            "close": 199.04
          },
          {
            "date": "2025-11-11",
            "close": 193.15
          },
          {
            "date": "2025-11-12",
            "close": 193.79
          },
          {
            "date": "2025-11-13",
            "close": 186.85
          },
          {
            "date": "2025-11-14",
            "close": 190.16
          },
          {
            "date": "2025-11-17",
            "close": 186.59
          },
          {
            "date": "2025-11-18",
            "close": 181.35
          },
          {
            "date": "2025-11-19",
            "close": 186.51
          },
          {
            "date": "2025-11-20",
            "close": 180.63
          },
          {
            "date": "2025-11-21",
            "close": 178.87
          },
          {
            "date": "2025-11-24",
            "close": 182.54
          },
          {
            "date": "2025-11-25",
            "close": 177.81
          },
          {
            "date": "2025-11-26",
            "close": 180.25
          },
          {
            "date": "2025-11-28",
            "close": 176.99
          },
          {
            "date": "2025-12-01",
            "close": 179.91
          },
          {
            "date": "2025-12-02",
            "close": 181.45
          },
          {
            "date": "2025-12-03",
            "close": 179.58
          },
          {
            "date": "2025-12-04",
            "close": 183.38
          },
          {
            "date": "2025-12-05",
            "close": 182.41
          },
          {
            "date": "2025-12-08",
            "close": 185.55
          },
          {
            "date": "2025-12-09",
            "close": 184.97
          },
          {
            "date": "2025-12-10",
            "close": 183.78
          },
          {
            "date": "2025-12-11",
            "close": 180.93
          },
          {
            "date": "2025-12-12",
            "close": 175.02
          },
          {
            "date": "2025-12-15",
            "close": 176.29
          },
          {
            "date": "2025-12-16",
            "close": 177.72
          },
          {
            "date": "2025-12-17",
            "close": 170.94
          },
          {
            "date": "2025-12-18",
            "close": 174.14
          },
          {
            "date": "2025-12-19",
            "close": 180.99
          },
          {
            "date": "2025-12-22",
            "close": 183.69
          },
          {
            "date": "2025-12-23",
            "close": 189.21
          },
          {
            "date": "2025-12-24",
            "close": 188.61
          },
          {
            "date": "2025-12-26",
            "close": 190.53
          },
          {
            "date": "2025-12-29",
            "close": 188.22
          },
          {
            "date": "2025-12-30",
            "close": 187.54
          },
          {
            "date": "2025-12-31",
            "close": 186.5
          },
          {
            "date": "2026-01-02",
            "close": 188.85
          },
          {
            "date": "2026-01-05",
            "close": 188.12
          }
        ],
        "valuationMetrics": {
          "peRatio": 46.564354,
          "pbRatio": 38.454617,
          "psRatio": 24.474236,
          "evToEbitda": 40.121,
          "marketCap": 4580157423616,
          "lastUpdated": "2026-01-06T17:19:48.182891"
        }
      },
      "category": "guru",
      "metadata": {
        "knownFor": "Corporate raider",
        "since": 1968,
        "type": "holding company"
      }
    },
    {
      "fundName": "Bridgewater Associates, LP",
      "fundCik": "0001350694",
      "mostPurchased": {
        "ticker": "IEP",
        "companyName": "ISHARES TR",
        "cusip": "464287200",
        "value": 2710196490,
        "shares": 4049300,
        "percentOfPortfolio": 10.616698411429939,
        "positionChange": {
          "previousQuarter": {
            "value": 1434123775,
            "shares": 2309750,
            "percentOfPortfolio": 5.784690022092807
          },
          "currentQuarter": {
            "value": 2710196490,
            "shares": 4049300,
            "percentOfPortfolio": 10.616698411429939
          },
          "change": {
            "valueChange": 1276072715,
            "sharesChange": 1739550,
            "percentChange": 88.97925947849237
          }
        },
        "priceHistory": [
          {
            "date": "2025-10-08",
            "close": 7.81
          },
          {
            "date": "2025-10-09",
            "close": 7.74
          },
          {
            "date": "2025-10-10",
            "close": 7.65
          },
          {
            "date": "2025-10-13",
            "close": 7.76
          },
          {
            "date": "2025-10-14",
            "close": 7.72
          },
          {
            "date": "2025-10-15",
            "close": 7.68
          },
          {
            "date": "2025-10-16",
            "close": 7.63
          },
          {
            "date": "2025-10-17",
            "close": 7.75
          },
          {
            "date": "2025-10-20",
            "close": 7.82
          },
          {
            "date": "2025-10-21",
            "close": 7.71
          },
          {
            "date": "2025-10-22",
            "close": 7.71
          },
          {
            "date": "2025-10-23",
            "close": 7.72
          },
          {
            "date": "2025-10-24",
            "close": 7.73
          },
          {
            "date": "2025-10-27",
            "close": 7.67
          },
          {
            "date": "2025-10-28",
            "close": 7.7
          },
          {
            "date": "2025-10-29",
            "close": 7.63
          },
          {
            "date": "2025-10-30",
            "close": 7.61
          },
          {
            "date": "2025-10-31",
            "close": 7.6
          },
          {
            "date": "2025-11-03",
            "close": 7.6
          },
          {
            "date": "2025-11-04",
            "close": 7.65
          },
          {
            "date": "2025-11-05",
            "close": 8.33
          },
          {
            "date": "2025-11-06",
            "close": 8.63
          },
          {
            "date": "2025-11-07",
            "close": 8.34
          },
          {
            "date": "2025-11-10",
            "close": 8.49
          },
          {
            "date": "2025-11-11",
            "close": 8.54
          },
          {
            "date": "2025-11-12",
            "close": 8.49
          },
          {
            "date": "2025-11-13",
            "close": 8.28
          },
          {
            "date": "2025-11-14",
            "close": 8.25
          },
          {
            "date": "2025-11-17",
            "close": 7.93
          },
          {
            "date": "2025-11-18",
            "close": 7.98
          },
          {
            "date": "2025-11-19",
            "close": 7.83
          },
          {
            "date": "2025-11-20",
            "close": 7.67
          },
          {
            "date": "2025-11-21",
            "close": 7.76
          },
          {
            "date": "2025-11-24",
            "close": 7.66
          },
          {
            "date": "2025-11-25",
            "close": 7.82
          },
          {
            "date": "2025-11-26",
            "close": 8
          },
          {
            "date": "2025-11-28",
            "close": 8.12
          },
          {
            "date": "2025-12-01",
            "close": 8.08
          },
          {
            "date": "2025-12-02",
            "close": 8.01
          },
          {
            "date": "2025-12-03",
            "close": 8.09
          },
          {
            "date": "2025-12-04",
            "close": 8.06
          },
          {
            "date": "2025-12-05",
            "close": 7.9
          },
          {
            "date": "2025-12-08",
            "close": 7.73
          },
          {
            "date": "2025-12-09",
            "close": 7.65
          },
          {
            "date": "2025-12-10",
            "close": 7.65
          },
          {
            "date": "2025-12-11",
            "close": 7.77
          },
          {
            "date": "2025-12-12",
            "close": 7.73
          },
          {
            "date": "2025-12-15",
            "close": 7.75
          },
          {
            "date": "2025-12-16",
            "close": 7.65
          },
          {
            "date": "2025-12-17",
            "close": 7.68
          },
          {
            "date": "2025-12-18",
            "close": 7.65
          },
          {
            "date": "2025-12-19",
            "close": 7.68
          },
          {
            "date": "2025-12-22",
            "close": 7.37
          },
          {
            "date": "2025-12-23",
            "close": 7.25
          },
          {
            "date": "2025-12-24",
            "close": 7.37
          },
          {
            "date": "2025-12-26",
            "close": 7.6
          },
          {
            "date": "2025-12-29",
            "close": 7.3
          },
          {
            "date": "2025-12-30",
            "close": 7.3
          },
          {
            "date": "2025-12-31",
            "close": 7.55
          },
          {
            "date": "2026-01-02",
            "close": 7.48
          },
          {
            "date": "2026-01-05",
            "close": 7.77
          }
        ],
        "valuationMetrics": {
          "peRatio": null,
          "pbRatio": 1.7050691,
          "psRatio": 0.5037939,
          "evToEbitda": 31.668,
          "marketCap": 4663620096,
          "lastUpdated": "2026-01-06T17:19:48.712051"
        }
      },
      "category": "guru",
      "metadata": {
        "knownFor": "Macro hedge fund pioneer",
        "since": 1975,
        "type": "hedge fund"
      }
    },
    {
      "fundName": "Soros Fund Management LLC",
      "fundCik": "0001029160",
      "mostPurchased": {
        "ticker": "AMZN",
        "companyName": "AMAZON COM INC",
        "cusip": "023135106",
        "value": 488803880,
        "shares": 2226187,
        "percentOfPortfolio": 6.962285352915207,
        "positionChange": {
          "previousQuarter": {
            "value": 83995217,
            "shares": 382858,
            "percentOfPortfolio": 1.0544158443813383
          },
          "currentQuarter": {
            "value": 488803880,
            "shares": 2226187,
            "percentOfPortfolio": 6.962285352915207
          },
          "change": {
            "valueChange": 404808663,
            "sharesChange": 1843329,
            "percentChange": 481.9425170364165
          }
        },
        "priceHistory": [
          {
            "date": "2025-10-08",
            "close": 225.22
          },
          {
            "date": "2025-10-09",
            "close": 227.74
          },
          {
            "date": "2025-10-10",
            "close": 216.37
          },
          {
            "date": "2025-10-13",
            "close": 220.07
          },
          {
            "date": "2025-10-14",
            "close": 216.39
          },
          {
            "date": "2025-10-15",
            "close": 215.57
          },
          {
            "date": "2025-10-16",
            "close": 214.47
          },
          {
            "date": "2025-10-17",
            "close": 213.04
          },
          {
            "date": "2025-10-20",
            "close": 216.48
          },
          {
            "date": "2025-10-21",
            "close": 222.03
          },
          {
            "date": "2025-10-22",
            "close": 217.95
          },
          {
            "date": "2025-10-23",
            "close": 221.09
          },
          {
            "date": "2025-10-24",
            "close": 224.21
          },
          {
            "date": "2025-10-27",
            "close": 226.97
          },
          {
            "date": "2025-10-28",
            "close": 229.25
          },
          {
            "date": "2025-10-29",
            "close": 230.3
          },
          {
            "date": "2025-10-30",
            "close": 222.86
          },
          {
            "date": "2025-10-31",
            "close": 244.22
          },
          {
            "date": "2025-11-03",
            "close": 254
          },
          {
            "date": "2025-11-04",
            "close": 249.32
          },
          {
            "date": "2025-11-05",
            "close": 250.2
          },
          {
            "date": "2025-11-06",
            "close": 243.04
          },
          {
            "date": "2025-11-07",
            "close": 244.41
          },
          {
            "date": "2025-11-10",
            "close": 248.4
          },
          {
            "date": "2025-11-11",
            "close": 249.1
          },
          {
            "date": "2025-11-12",
            "close": 244.2
          },
          {
            "date": "2025-11-13",
            "close": 237.58
          },
          {
            "date": "2025-11-14",
            "close": 234.69
          },
          {
            "date": "2025-11-17",
            "close": 232.87
          },
          {
            "date": "2025-11-18",
            "close": 222.55
          },
          {
            "date": "2025-11-19",
            "close": 222.69
          },
          {
            "date": "2025-11-20",
            "close": 217.14
          },
          {
            "date": "2025-11-21",
            "close": 220.69
          },
          {
            "date": "2025-11-24",
            "close": 226.28
          },
          {
            "date": "2025-11-25",
            "close": 229.67
          },
          {
            "date": "2025-11-26",
            "close": 229.16
          },
          {
            "date": "2025-11-28",
            "close": 233.22
          },
          {
            "date": "2025-12-01",
            "close": 233.88
          },
          {
            "date": "2025-12-02",
            "close": 234.42
          },
          {
            "date": "2025-12-03",
            "close": 232.38
          },
          {
            "date": "2025-12-04",
            "close": 229.11
          },
          {
            "date": "2025-12-05",
            "close": 229.53
          },
          {
            "date": "2025-12-08",
            "close": 226.89
          },
          {
            "date": "2025-12-09",
            "close": 227.92
          },
          {
            "date": "2025-12-10",
            "close": 231.78
          },
          {
            "date": "2025-12-11",
            "close": 230.28
          },
          {
            "date": "2025-12-12",
            "close": 226.19
          },
          {
            "date": "2025-12-15",
            "close": 222.54
          },
          {
            "date": "2025-12-16",
            "close": 222.56
          },
          {
            "date": "2025-12-17",
            "close": 221.27
          },
          {
            "date": "2025-12-18",
            "close": 226.76
          },
          {
            "date": "2025-12-19",
            "close": 227.35
          },
          {
            "date": "2025-12-22",
            "close": 228.43
          },
          {
            "date": "2025-12-23",
            "close": 232.14
          },
          {
            "date": "2025-12-24",
            "close": 232.38
          },
          {
            "date": "2025-12-26",
            "close": 232.52
          },
          {
            "date": "2025-12-29",
            "close": 232.07
          },
          {
            "date": "2025-12-30",
            "close": 232.53
          },
          {
            "date": "2025-12-31",
            "close": 230.82
          },
          {
            "date": "2026-01-02",
            "close": 226.5
          },
          {
            "date": "2026-01-05",
            "close": 233.06
          }
        ],
        "valuationMetrics": {
          "peRatio": 32.87165,
          "pbRatio": 6.7383695,
          "psRatio": 3.6038673,
          "evToEbitda": 18.309,
          "marketCap": 2491461664768,
          "lastUpdated": "2026-01-06T17:19:49.289488"
        }
      },
      "category": "guru",
      "metadata": {
        "knownFor": "Legendary macro trader",
        "since": 1970,
        "type": "hedge fund"
      }
    },
    {
      "fundName": "Baupost Group LLC",
      "fundCik": "0001061768",
      "mostPurchased": {
        "ticker": "",
        "companyName": "UNION PAC CORP",
        "cusip": "907818108",
        "value": 353658,
        "shares": 1496204,
        "percentOfPortfolio": 7.382017715606818,
        "positionChange": {
          "previousQuarter": {
            "value": 0,
            "shares": 0,
            "percentOfPortfolio": 0
          },
          "currentQuarter": {
            "value": 353658,
            "shares": 1496204,
            "percentOfPortfolio": 7.382017715606818
          },
          "change": {
            "valueChange": 353658,
            "sharesChange": 1496204,
            "percentChange": null
          }
        },
        "priceHistory": [],
        "valuationMetrics": {
          "peRatio": null,
          "pbRatio": null,
          "psRatio": null,
          "evToEbitda": null,
          "marketCap": 0,
          "lastUpdated": ""
        }
      },
      "category": "guru",
      "metadata": {
        "knownFor": "Value investing",
        "since": 1982,
        "type": "hedge fund"
      }
    },
    {
      "fundName": "Third Point LLC",
      "fundCik": "0001040273",
      "mostPurchased": {
        "ticker": "SPY",
        "companyName": "SPDR S&P 500 ETF TR",
        "cusip": "78462F103",
        "value": 582907500,
        "shares": 875000,
        "percentOfPortfolio": 6.484651465672004,
        "positionChange": {
          "previousQuarter": {
            "value": 0,
            "shares": 0,
            "percentOfPortfolio": 0
          },
          "currentQuarter": {
            "value": 582907500,
            "shares": 875000,
            "percentOfPortfolio": 6.484651465672004
          },
          "change": {
            "valueChange": 582907500,
            "sharesChange": 875000,
            "percentChange": null
          }
        },
        "priceHistory": [
          {
            "date": "2025-10-08",
            "close": 671.13
          },
          {
            "date": "2025-10-09",
            "close": 669.18
          },
          {
            "date": "2025-10-10",
            "close": 651.1
          },
          {
            "date": "2025-10-13",
            "close": 661.09
          },
          {
            "date": "2025-10-14",
            "close": 660.28
          },
          {
            "date": "2025-10-15",
            "close": 663.21
          },
          {
            "date": "2025-10-16",
            "close": 658.69
          },
          {
            "date": "2025-10-17",
            "close": 662.43
          },
          {
            "date": "2025-10-20",
            "close": 669.32
          },
          {
            "date": "2025-10-21",
            "close": 669.31
          },
          {
            "date": "2025-10-22",
            "close": 665.83
          },
          {
            "date": "2025-10-23",
            "close": 669.78
          },
          {
            "date": "2025-10-24",
            "close": 675.25
          },
          {
            "date": "2025-10-27",
            "close": 683.22
          },
          {
            "date": "2025-10-28",
            "close": 685.04
          },
          {
            "date": "2025-10-29",
            "close": 685.36
          },
          {
            "date": "2025-10-30",
            "close": 677.83
          },
          {
            "date": "2025-10-31",
            "close": 680.05
          },
          {
            "date": "2025-11-03",
            "close": 681.33
          },
          {
            "date": "2025-11-04",
            "close": 673.25
          },
          {
            "date": "2025-11-05",
            "close": 675.58
          },
          {
            "date": "2025-11-06",
            "close": 668.34
          },
          {
            "date": "2025-11-07",
            "close": 668.99
          },
          {
            "date": "2025-11-10",
            "close": 679.43
          },
          {
            "date": "2025-11-11",
            "close": 680.99
          },
          {
            "date": "2025-11-12",
            "close": 681.37
          },
          {
            "date": "2025-11-13",
            "close": 670.06
          },
          {
            "date": "2025-11-14",
            "close": 669.95
          },
          {
            "date": "2025-11-17",
            "close": 663.71
          },
          {
            "date": "2025-11-18",
            "close": 658.14
          },
          {
            "date": "2025-11-19",
            "close": 660.68
          },
          {
            "date": "2025-11-20",
            "close": 650.61
          },
          {
            "date": "2025-11-21",
            "close": 657.09
          },
          {
            "date": "2025-11-24",
            "close": 666.76
          },
          {
            "date": "2025-11-25",
            "close": 673.03
          },
          {
            "date": "2025-11-26",
            "close": 677.68
          },
          {
            "date": "2025-11-28",
            "close": 681.38
          },
          {
            "date": "2025-12-01",
            "close": 678.27
          },
          {
            "date": "2025-12-02",
            "close": 679.52
          },
          {
            "date": "2025-12-03",
            "close": 681.88
          },
          {
            "date": "2025-12-04",
            "close": 682.37
          },
          {
            "date": "2025-12-05",
            "close": 683.67
          },
          {
            "date": "2025-12-08",
            "close": 681.62
          },
          {
            "date": "2025-12-09",
            "close": 681.03
          },
          {
            "date": "2025-12-10",
            "close": 685.54
          },
          {
            "date": "2025-12-11",
            "close": 687.14
          },
          {
            "date": "2025-12-12",
            "close": 679.75
          },
          {
            "date": "2025-12-15",
            "close": 678.72
          },
          {
            "date": "2025-12-16",
            "close": 676.87
          },
          {
            "date": "2025-12-17",
            "close": 669.42
          },
          {
            "date": "2025-12-18",
            "close": 674.48
          },
          {
            "date": "2025-12-19",
            "close": 680.59
          },
          {
            "date": "2025-12-22",
            "close": 684.83
          },
          {
            "date": "2025-12-23",
            "close": 687.96
          },
          {
            "date": "2025-12-24",
            "close": 690.38
          },
          {
            "date": "2025-12-26",
            "close": 690.31
          },
          {
            "date": "2025-12-29",
            "close": 687.85
          },
          {
            "date": "2025-12-30",
            "close": 687.01
          },
          {
            "date": "2025-12-31",
            "close": 681.92
          },
          {
            "date": "2026-01-02",
            "close": 683.17
          },
          {
            "date": "2026-01-05",
            "close": 687.72
          }
        ],
        "valuationMetrics": {
          "peRatio": 27.738039,
          "pbRatio": 1.6022552,
          "psRatio": null,
          "evToEbitda": null,
          "marketCap": 631177019392,
          "lastUpdated": "2026-01-06T17:19:49.845133"
        }
      },
      "category": "guru",
      "metadata": {
        "knownFor": "Activist investor",
        "since": 1995,
        "type": "hedge fund"
      }
    }
  ]
}